LICENSE.md
README.rst
setup.py
SpatialGlue/SpatialGlue_pyG.py
SpatialGlue/model.py
SpatialGlue/preprocess.py
SpatialGlue/utils.py
SpatialGlue.egg-info/PKG-INFO
SpatialGlue.egg-info/SOURCES.txt
SpatialGlue.egg-info/dependency_links.txt
SpatialGlue.egg-info/not-zip-safe
SpatialGlue.egg-info/requires.txt
SpatialGlue.egg-info/top_level.txt