Metadata-Version: 2.1
Name: SpatialGlue
Version: 1.1.5
Summary: Deciphering spatial domains from spatial multi-omics with SpatialGlue
Home-page: https://github.com/JinmiaoChenLab/SpatialGlue
Author: Yahui Long
Author-email: longyh@immunol.a-star.edu.sg
License: MIT
License-File: LICENSE.md
